README.md
setup.cfg
setup.py
gremlinc/__init__.py
gremlinc/gremlins.py
gremlinc.egg-info/PKG-INFO
gremlinc.egg-info/SOURCES.txt
gremlinc.egg-info/dependency_links.txt
gremlinc.egg-info/not-zip-safe
gremlinc.egg-info/top_level.txt