Metadata-Version: 2.1
Name: gremlinc
Version: 0.2
Summary: Handle gremlin characters (zero width / invisible).
Home-page: https://github.com/marinko-peso/gremlinc
Author: Marinko Peso
Author-email: marinko.peso@gmail.com
License: MIT
Keywords: zero width characters gremlins
Platform: UNKNOWN
Classifier: Intended Audience :: Developers
Classifier: License :: OSI Approved :: MIT License
Classifier: Operating System :: OS Independent
Classifier: Programming Language :: Python
Classifier: Programming Language :: Python :: 2
Classifier: Programming Language :: Python :: 2.7
Classifier: Programming Language :: Python :: 3
Classifier: Programming Language :: Python :: 3.6
